{"id":"BOXW54KG--------------------------","final":{"description":"女子54公斤级 - 决赛","allMatch":[{"competitor1":{"countryEN":"CHN","name":"CHANG Y","score":"5","isWinner":true},"competitor2":{"countryEN":"TUR","name":"AKBAS H","score":"0","isWinner":false}}]},"final2":{"description":null,"allMatch":[]},"halfFinal":{"description":"女子54公斤级 - 半决赛","allMatch":[{"competitor1":{"countryEN":"CHN","name":"CHANG Y","score":"3","isWinner":true},"competitor2":{"countryEN":"PRK","name":"PANG C","score":"2","isWinner":false}},{"competitor1":{"countryEN":"TUR","name":"AKBAS H","score":"3","isWinner":true},"competitor2":{"countryEN":"KOR","name":"IM A","score":"2","isWinner":false}}]},"qFinal":{"description":"女子54公斤级 - 1/4决赛","allMatch":[{"competitor1":{"countryEN":"BUL","name":"PETROVA S","score":"1","isWinner":false},"competitor2":{"countryEN":"CHN","name":"CHANG Y","score":"4","isWinner":true}},{"competitor1":{"countryEN":"MAR","name":"BERTAL W","score":"0","isWinner":false},"competitor2":{"countryEN":"PRK","name":"PANG C","score":"4","isWinner":true}},{"competitor1":{"countryEN":"TUR","name":"AKBAS H","score":"5","isWinner":true},"competitor2":{"countryEN":"MGL","name":"MUNGUNTSETSEG E","score":"0","isWinner":false}},{"competitor1":{"countryEN":"KOR","name":"IM A","score":"3","isWinner":true},"competitor2":{"countryEN":"COL","name":"ARIAS CASTANEDA YM","score":"2","isWinner":false}}]}}