{"id":"FENWFOIL--------------------------","final":{"description":"女子个人花剑金牌赛","allMatch":[{"competitor1":{"countryEN":"USA","countryCN":"美国","score":"6","isWinner":false},"competitor2":{"countryEN":"USA","countryCN":"美国","score":"15","isWinner":true}}]},"final2":{"description":"女子个人花剑铜牌赛","allMatch":[{"competitor1":{"countryEN":"CAN","countryCN":"加拿大","score":"15","isWinner":true},"competitor2":{"countryEN":"ITA","countryCN":"意大利","score":"12","isWinner":false}}]},"halfFinal":{"description":"女子个人花剑半决赛2","allMatch":[{"competitor1":{"countryEN":"USA","countryCN":"美国","score":"15","isWinner":true},"competitor2":{"countryEN":"CAN","countryCN":"加拿大","score":"9","isWinner":false}},{"competitor1":{"countryEN":"ITA","countryCN":"意大利","score":"10","isWinner":false},"competitor2":{"countryEN":"USA","countryCN":"美国","score":"15","isWinner":true}}]},"qFinal":{"description":"女子个人花剑8强","allMatch":[{"competitor1":{"countryEN":"ITA","countryCN":"意大利","score":"14","isWinner":false},"competitor2":{"countryEN":"USA","countryCN":"美国","score":"15","isWinner":true}},{"competitor1":{"countryEN":"CAN","countryCN":"加拿大","score":"15","isWinner":true},"competitor2":{"countryEN":"ITA","countryCN":"意大利","score":"14","isWinner":false}},{"competitor1":{"countryEN":"ITA","countryCN":"意大利","score":"15","isWinner":true},"competitor2":{"countryEN":"GER","countryCN":"德国","score":"12","isWinner":false}},{"competitor1":{"countryEN":"HUN","countryCN":"匈牙利","score":"4","isWinner":false},"competitor2":{"countryEN":"USA","countryCN":"美国","score":"15","isWinner":true}}]}}