{"id":"WREMGR67KG------------------------","final":{"description":"男子古典式67公斤级决赛","allMatch":[{"competitor1":{"countryEN":"UKR","countryCN":"乌克兰","score":null,"isWinner":false},"competitor2":{"countryEN":"IRI","countryCN":"伊朗","score":null,"isWinner":true}}]},"final2":{"description":null,"allMatch":[]},"halfFinal":{"description":"男子古典式67公斤级半决赛","allMatch":[{"competitor1":{"countryEN":"AZE","countryCN":"阿塞拜疆","score":null,"isWinner":false},"competitor2":{"countryEN":"UKR","countryCN":"乌克兰","score":null,"isWinner":true}},{"competitor1":{"countryEN":"ARM","countryCN":"亚美尼亚","score":null,"isWinner":false},"competitor2":{"countryEN":"IRI","countryCN":"伊朗","score":null,"isWinner":true}}]},"qFinal":{"description":"男子古典式67公斤级1/4决赛","allMatch":[{"competitor1":{"countryEN":"AZE","countryCN":"阿塞拜疆","score":null,"isWinner":true},"competitor2":{"countryEN":"MDA","countryCN":"摩尔多瓦","score":null,"isWinner":false}},{"competitor1":{"countryEN":"KGZ","countryCN":"吉尔吉斯斯坦","score":null,"isWinner":false},"competitor2":{"countryEN":"UKR","countryCN":"乌克兰","score":null,"isWinner":true}},{"competitor1":{"countryEN":"ARM","countryCN":"亚美尼亚","score":null,"isWinner":true},"competitor2":{"countryEN":"FRA","countryCN":"法国","score":null,"isWinner":false}},{"competitor1":{"countryEN":"IRI","countryCN":"伊朗","score":null,"isWinner":true},"competitor2":{"countryEN":"CUB","countryCN":"古巴","score":null,"isWinner":false}}]}}