{"resultCombines":[{"stateName":"A组","results":[{"startDate":"2024-07-24T17:00","competitor1":{"countryEN":"GUI","name":"Guinea","score":"1","isWinner":false},"competitor2":{"countryEN":"NZL","name":"New Zealand","score":"2","isWinner":true}},{"startDate":"2024-07-24T21:00","competitor1":{"countryEN":"FRA","name":"France","score":"3","isWinner":true},"competitor2":{"countryEN":"USA","name":"United States","score":"0","isWinner":false}},{"startDate":"2024-07-27T19:00","competitor1":{"countryEN":"NZL","name":"New Zealand","score":"1","isWinner":false},"competitor2":{"countryEN":"USA","name":"United States","score":"4","isWinner":true}},{"startDate":"2024-07-27T21:00","competitor1":{"countryEN":"FRA","name":"France","score":"1","isWinner":true},"competitor2":{"countryEN":"GUI","name":"Guinea","score":"0","isWinner":false}},{"startDate":"2024-07-30T19:00","competitor1":{"countryEN":"USA","name":"United States","score":"3","isWinner":true},"competitor2":{"countryEN":"GUI","name":"Guinea","score":"0","isWinner":false}},{"startDate":"2024-07-30T19:00","competitor1":{"countryEN":"NZL","name":"New Zealand","score":"0","isWinner":false},"competitor2":{"countryEN":"FRA","name":"France","score":"3","isWinner":true}}]},{"stateName":"B组","results":[{"startDate":"2024-07-24T15:00","competitor1":{"countryEN":"ARG","name":"Argentina","score":"1","isWinner":false},"competitor2":{"countryEN":"MAR","name":"Morocco","score":"2","isWinner":true}},{"startDate":"2024-07-24T19:00","competitor1":{"countryEN":"IRQ","name":"Iraq","score":"2","isWinner":true},"competitor2":{"countryEN":"UKR","name":"Ukraine","score":"1","isWinner":false}},{"startDate":"2024-07-27T15:00","competitor1":{"countryEN":"ARG","name":"Argentina","score":"3","isWinner":true},"competitor2":{"countryEN":"IRQ","name":"Iraq","score":"1","isWinner":false}},{"startDate":"2024-07-27T17:00","competitor1":{"countryEN":"UKR","name":"Ukraine","score":"2","isWinner":true},"competitor2":{"countryEN":"MAR","name":"Morocco","score":"1","isWinner":false}},{"startDate":"2024-07-30T17:00","competitor1":{"countryEN":"MAR","name":"Morocco","score":"3","isWinner":true},"competitor2":{"countryEN":"IRQ","name":"Iraq","score":"0","isWinner":false}},{"startDate":"2024-07-30T17:00","competitor1":{"countryEN":"UKR","name":"Ukraine","score":"0","isWinner":false},"competitor2":{"countryEN":"ARG","name":"Argentina","score":"2","isWinner":true}}]},{"stateName":"C组","results":[{"startDate":"2024-07-24T15:00","competitor1":{"countryEN":"UZB","name":"Uzbekistan","score":"1","isWinner":false},"competitor2":{"countryEN":"ESP","name":"Spain","score":"2","isWinner":true}},{"startDate":"2024-07-24T17:00","competitor1":{"countryEN":"EGY","name":"Egypt","score":"0","isWinner":false},"competitor2":{"countryEN":"DOM","name":"Dominican Republic","score":"0","isWinner":false}},{"startDate":"2024-07-27T15:00","competitor1":{"countryEN":"DOM","name":"Dominican Republic","score":"1","isWinner":false},"competitor2":{"countryEN":"ESP","name":"Spain","score":"3","isWinner":true}},{"startDate":"2024-07-27T17:00","competitor1":{"countryEN":"UZB","name":"Uzbekistan","score":"0","isWinner":false},"competitor2":{"countryEN":"EGY","name":"Egypt","score":"1","isWinner":true}},{"startDate":"2024-07-30T15:00","competitor1":{"countryEN":"DOM","name":"Dominican Republic","score":"1","isWinner":false},"competitor2":{"countryEN":"UZB","name":"Uzbekistan","score":"1","isWinner":false}},{"startDate":"2024-07-30T15:00","competitor1":{"countryEN":"ESP","name":"Spain","score":"1","isWinner":false},"competitor2":{"countryEN":"EGY","name":"Egypt","score":"2","isWinner":true}}]},{"stateName":"D组","results":[{"startDate":"2024-07-24T19:00","competitor1":{"countryEN":"JPN","name":"Japan","score":"5","isWinner":true},"competitor2":{"countryEN":"PAR","name":"Paraguay","score":"0","isWinner":false}},{"startDate":"2024-07-24T21:00","competitor1":{"countryEN":"MLI","name":"Mali","score":"1","isWinner":false},"competitor2":{"countryEN":"ISR","name":"Israel","score":"1","isWinner":false}},{"startDate":"2024-07-27T19:00","competitor1":{"countryEN":"ISR","name":"Israel","score":"2","isWinner":false},"competitor2":{"countryEN":"PAR","name":"Paraguay","score":"4","isWinner":true}},{"startDate":"2024-07-27T21:00","competitor1":{"countryEN":"JPN","name":"Japan","score":"1","isWinner":true},"competitor2":{"countryEN":"MLI","name":"Mali","score":"0","isWinner":false}},{"startDate":"2024-07-30T21:00","competitor1":{"countryEN":"PAR","name":"Paraguay","score":"1","isWinner":true},"competitor2":{"countryEN":"MLI","name":"Mali","score":"0","isWinner":false}},{"startDate":"2024-07-30T21:00","competitor1":{"countryEN":"ISR","name":"Israel","score":"0","isWinner":false},"competitor2":{"countryEN":"JPN","name":"Japan","score":"1","isWinner":true}}]},{"stateName":"1/4决赛","results":[{"startDate":"2024-08-02T15:00","competitor1":{"countryEN":"MAR","name":"Morocco","score":"4","isWinner":true},"competitor2":{"countryEN":"USA","name":"United States","score":"0","isWinner":false}},{"startDate":"2024-08-02T17:00","competitor1":{"countryEN":"JPN","name":"Japan","score":"0","isWinner":false},"competitor2":{"countryEN":"ESP","name":"Spain","score":"3","isWinner":true}},{"startDate":"2024-08-02T19:00","competitor1":{"countryEN":"EGY","name":"Egypt","score":"1","isWinner":true},"competitor2":{"countryEN":"PAR","name":"Paraguay","score":"1","isWinner":false}},{"startDate":"2024-08-02T21:00","competitor1":{"countryEN":"FRA","name":"France","score":"1","isWinner":true},"competitor2":{"countryEN":"ARG","name":"Argentina","score":"0","isWinner":false}}]},{"stateName":"半决赛","results":[{"startDate":"2024-08-05T18:00","competitor1":{"countryEN":"MAR","name":"Morocco","score":"1","isWinner":false},"competitor2":{"countryEN":"ESP","name":"Spain","score":"2","isWinner":true}},{"startDate":"2024-08-05T21:00","competitor1":{"countryEN":"FRA","name":"France","score":"3","isWinner":true},"competitor2":{"countryEN":"EGY","name":"Egypt","score":"1","isWinner":false}}]},{"stateName":"铜牌赛","results":[{"startDate":"2024-08-08T17:00","competitor1":{"countryEN":"EGY","name":"Egypt","score":"0","isWinner":false},"competitor2":{"countryEN":"MAR","name":"Morocco","score":"6","isWinner":true}}]},{"stateName":"金牌赛","results":[{"startDate":"2024-08-09T18:00","competitor1":{"countryEN":"FRA","name":"France","score":"3","isWinner":false},"competitor2":{"countryEN":"ESP","name":"Spain","score":"5","isWinner":true}}]}]}