{"resultCombines":[{"stateName":"5-6名排名赛","results":[{"startDate":"2024-08-03T16:10","competitor1":{"countryEN":"HUN","name":"Hungary","score":"39","isWinner":false},"competitor2":{"countryEN":"USA","name":"United States","score":"45","isWinner":true}}]},{"stateName":"5-8名排名赛","results":[{"startDate":"2024-08-03T14:30","competitor1":{"countryEN":"HUN","name":"Hungary","score":"45","isWinner":true},"competitor2":{"countryEN":"ITA","name":"Italy","score":"35","isWinner":false}},{"startDate":"2024-08-03T14:30","competitor1":{"countryEN":"USA","name":"United States","score":"45","isWinner":true},"competitor2":{"countryEN":"ALG","name":"Algeria","score":"28","isWinner":false}}]},{"stateName":"7-8名排名赛","results":[{"startDate":"2024-08-03T16:10","competitor1":{"countryEN":"ITA","name":"Italy","score":"45","isWinner":true},"competitor2":{"countryEN":"ALG","name":"Algeria","score":"27","isWinner":false}}]},{"stateName":"8强","results":[{"startDate":"2024-08-03T13:00","competitor1":{"countryEN":"HUN","name":"Hungary","score":"37","isWinner":false},"competitor2":{"countryEN":"JPN","name":"Japan","score":"45","isWinner":true}},{"startDate":"2024-08-03T13:00","competitor1":{"countryEN":"KOR","name":"Korea","score":"45","isWinner":true},"competitor2":{"countryEN":"USA","name":"United States","score":"35","isWinner":false}},{"startDate":"2024-08-03T13:00","competitor1":{"countryEN":"ITA","name":"Italy","score":"37","isWinner":false},"competitor2":{"countryEN":"UKR","name":"Ukraine","score":"45","isWinner":true}},{"startDate":"2024-08-03T13:00","competitor1":{"countryEN":"ALG","name":"Algeria","score":"32","isWinner":false},"competitor2":{"countryEN":"FRA","name":"France","score":"45","isWinner":true}}]},{"stateName":"半决赛1","results":[{"startDate":"2024-08-03T15:20","competitor1":{"countryEN":"KOR","name":"Korea","score":"45","isWinner":true},"competitor2":{"countryEN":"FRA","name":"France","score":"36","isWinner":false}}]},{"stateName":"半决赛2","results":[{"startDate":"2024-08-03T15:20","competitor1":{"countryEN":"UKR","name":"Ukraine","score":"45","isWinner":true},"competitor2":{"countryEN":"JPN","name":"Japan","score":"32","isWinner":false}}]},{"stateName":"铜牌赛","results":[{"startDate":"2024-08-03T19:00","competitor1":{"countryEN":"FRA","name":"France","score":"40","isWinner":false},"competitor2":{"countryEN":"JPN","name":"Japan","score":"45","isWinner":true}}]},{"stateName":"金牌赛","results":[{"startDate":"2024-08-03T20:00","competitor1":{"countryEN":"KOR","name":"Korea","score":"42","isWinner":false},"competitor2":{"countryEN":"UKR","name":"Ukraine","score":"45","isWinner":true}}]}]}